dbnomics_pptx_tools/__init__.py
dbnomics_pptx_tools/cache.py
dbnomics_pptx_tools/data_archive.py
dbnomics_pptx_tools/data_loader.py
dbnomics_pptx_tools/formatters.py
dbnomics_pptx_tools/metadata.py
dbnomics_pptx_tools/module_utils.py
dbnomics_pptx_tools/pptx_copy.py
dbnomics_pptx_tools/repo.py
dbnomics_pptx_tools/slides.py
dbnomics_pptx_tools/tables.py
dbnomics_pptx_tools/xml_utils.py
dbnomics_pptx_tools/charts/__init__.py
dbnomics_pptx_tools/charts/chart_data.py
dbnomics_pptx_tools/charts/data_labels.py
dbnomics_pptx_tools/charts/series.py
dbnomics_pptx_tools/charts/time_series_chart.py
dbnomics_pptx_tools/charts/utils.py
dbnomics_pptx_tools/charts/xy_chart.py
dbnomics_pptx_tools/cli/__init__.py
dbnomics_pptx_tools/cli/app.py
dbnomics_pptx_tools/cli/cli_utils.py
dbnomics_pptx_tools/cli/slide_expr.py
dbnomics_pptx_tools-0.2.19.dist-info/LICENSE
dbnomics_pptx_tools-0.2.19.dist-info/METADATA
dbnomics_pptx_tools-0.2.19.dist-info/WHEEL
dbnomics_pptx_tools-0.2.19.dist-info/entry_points.txt
dbnomics_pptx_tools-0.2.19.dist-info/top_level.txt
dbnomics_pptx_tools-0.2.19.dist-info/RECORD
