Metadata-Version: 2.1
Name: dbnomics-pptx-tools
Version: 0.2.19
Summary: DBnomics PowerPoint (pptx) tools
Author-email: Christophe Benz <christophe.benz@nomics.world>
License: GNU AFFERO GENERAL PUBLIC LICENSE
Project-URL: Homepage, https://git.nomics.world/dbnomics/dbnomics-pptx-tools
Project-URL: Bug Tracker, https://git.nomics.world/dbnomics/dbnomics-pptx-tools/-/issues
Classifier: Programming Language :: Python :: 3
Classifier: License :: OSI Approved :: GNU Affero General Public License v3 or later (AGPLv3+)
Classifier: Operating System :: OS Independent
Requires-Python: >=3.11
License-File: LICENSE
Requires-Dist: daiquiri
Requires-Dist: DBnomics
Requires-Dist: isodate
Requires-Dist: lxml
Requires-Dist: more-itertools
Requires-Dist: parsy
Requires-Dist: pydantic <2.0
Requires-Dist: python-pptx
Requires-Dist: python-slugify
Requires-Dist: PyYAML
Requires-Dist: requests
Requires-Dist: tabulate
Requires-Dist: typer[all]
Requires-Dist: webcolors
Provides-Extra: dev
Requires-Dist: black ; extra == 'dev'
Requires-Dist: mypy ; extra == 'dev'
Requires-Dist: pip-tools ; extra == 'dev'
Requires-Dist: pre-commit ; extra == 'dev'
Requires-Dist: ruff ; extra == 'dev'
Requires-Dist: types-python-slugify ; extra == 'dev'
Requires-Dist: types-PyYAML ; extra == 'dev'
Requires-Dist: types-requests ; extra == 'dev'
Requires-Dist: types-tabulate ; extra == 'dev'
